[{"id": 1, "src": 8, "dst": 4, "weight": 1.096971252032511}, {"id": 2, "src": 6, "dst": 1, "weight": 3.487094366009514}, {"id": 3, "src": 1, "dst": 8, "weight": 3.0484034075258326}, {"id": 4, "src": 6, "dst": 3, "weight": 0.6368719292690252}, {"id": 5, "src": 2, "dst": 3, "weight": 5.207423117534366}, {"id": 6, "src": 10, "dst": 8, "weight": 4.605147675335726}, {"id": 7, "src": 8, "dst": 3, "weight": 1.6893554550722658}, {"id": 8, "src": 9, "dst": 2, "weight": 6.479479336171115}, {"id": 9, "src": 4, "dst": 5, "weight": 1.955615989754548}, {"id": 10, "src": 9, "dst": 4, "weight": 5.471556115768339}, {"id": 11, "src": 4, "dst": 5, "weight": 1.3361203976908969}, {"id": 12, "src": 3, "dst": 8, "weight": 5.221358652165337}, {"id": 13, "src": 2, "dst": 5, "weight": 3.615619275730742}, {"id": 14, "src": 5, "dst": 1, "weight": 6.433388670555318}, {"id": 15, "src": 4, "dst": 2, "weight": 1.6014997474649737}, {"id": 16, "src": 8, "dst": 1, "weight": 3.0105561665067126}, {"id": 17, "src": 2, "dst": 10, "weight": 6.072250422128727}, {"id": 18, "src": 1, "dst": 4, "weight": 4.714126136529744}, {"id": 19, "src": 2, "dst": 6, "weight": 5.696447363168175}, {"id": 20, "src": 3, "dst": 5, "weight": 6.095694455819221}, {"id": 21, "src": 7, "dst": 9, "weight": 2.196873700648373}, {"id": 22, "src": 7, "dst": 10, "weight": 5.960366844629873}, {"id": 23, "src": 6, "dst": 1, "weight": 4.503445603775646}, {"id": 24, "src": 10, "dst": 6, "weight": 0.5051712377652202}, {"id": 25, "src": 4, "dst": 9, "weight": 4.479606235523557}, {"id": 26, "src": 5, "dst": 6, "weight": 0.8694732236451446}, {"id": 27, "src": 10, "dst": 5, "weight": 1.8094626213907599}, {"id": 28, "src": 2, "dst": 1, "weight": 0.8029796041223012}, {"id": 29, "src": 1, "dst": 7, "weight": 6.026169000287966}, {"id": 30, "src": 6, "dst": 8, "weight": 3.614900962250298}, {"id": 31, "src": 3, "dst": 7, "weight": 5.1581903382281915}, {"id": 32, "src": 1, "dst": 10, "weight": 2.007863222928891}, {"id": 33, "src": 2, "dst": 9, "weight": 3.169559793536264}, {"id": 34, "src": 5, "dst": 3, "weight": 1.641976180243327}, {"id": 35, "src": 7, "dst": 2, "weight": 1.8391159245530346}, {"id": 36, "src": 5, "dst": 10, "weight": 1.8279072032860653}, {"id": 37, "src": 9, "dst": 5, "weight": 3.002510147393902}, {"id": 38, "src": 1, "dst": 6, "weight": 0.5537142200587819}, {"id": 39, "src": 10, "dst": 4, "weight": 2.1680926376948273}, {"id": 40, "src": 10, "dst": 6, "weight": 5.240126739171817}, {"id": 41, "src": 7, "dst": 10, "weight": 4.063158104277443}, {"id": 42, "src": 6, "dst": 2, "weight": 2.2587836390586293}, {"id": 43, "src": 1, "dst": 6, "weight": 3.41606803038737}, {"id": 44, "src": 3, "dst": 7, "weight": 1.8629956090218527}, {"id": 45, "src": 2, "dst": 10, "weight": 5.562076214259282}, {"id": 46, "src": 6, "dst": 10, "weight": 2.832063318575812}, {"id": 47, "src": 2, "dst": 7, "weight": 2.4212938569045632}, {"id": 48, "src": 7, "dst": 6, "weight": 2.2505401702032954}, {"id": 49, "src": 1, "dst": 5, "weight": 1.7053579627171012}, {"id": 50, "src": 2, "dst": 10, "weight": 2.729140229448823}, {"id": 51, "src": 6, "dst": 2, "weight": 1.283189872180091}, {"id": 52, "src": 10, "dst": 1, "weight": 4.513814019999288}, {"id": 53, "src": 6, "dst": 9, "weight": 6.22429164142452}, {"id": 54, "src": 5, "dst": 9, "weight": 5.035030673151491}, {"id": 55, "src": 3, "dst": 1, "weight": 3.1308065114537706}, {"id": 56, "src": 2, "dst": 5, "weight": 4.879110713663318}, {"id": 57, "src": 4, "dst": 1, "weight": 0.6713987160419612}, {"id": 58, "src": 5, "dst": 3, "weight": 4.778252587728439}, {"id": 59, "src": 2, "dst": 1, "weight": 2.1056183321618196}, {"id": 60, "src": 2, "dst": 9, "weight": 4.312889602497985}, {"id": 61, "src": 7, "dst": 1, "weight": 3.9168796891287796}, {"id": 62, "src": 8, "dst": 7, "weight": 5.576491943696565}, {"id": 63, "src": 8, "dst": 9, "weight": 4.18915888629309}, {"id": 64, "src": 8, "dst": 6, "weight": 6.0576494507654}, {"id": 65, "src": 2, "dst": 1, "weight": 2.0826903664131846}, {"id": 66, "src": 7, "dst": 8, "weight": 4.820630591405236}, {"id": 67, "src": 5, "dst": 2, "weight": 6.182839632643223}, {"id": 68, "src": 6, "dst": 9, "weight": 6.210612258943663}, {"id": 69, "src": 8, "dst": 6, "weight": 4.463183054957124}, {"id": 70, "src": 6, "dst": 2, "weight": 3.503980154423455}, {"id": 71, "src": 2, "dst": 9, "weight": 3.2107739938709936}, {"id": 72, "src": 5, "dst": 7, "weight": 1.8304535531944603}, {"id": 73, "src": 10, "dst": 7, "weight": 6.144918838008958}, {"id": 74, "src": 5, "dst": 8, "weight": 5.624646596713255}, {"id": 75, "src": 6, "dst": 7, "weight": 0.7284454446227511}, {"id": 76, "src": 7, "dst": 9, "weight": 2.43028966136979}, {"id": 77, "src": 10, "dst": 5, "weight": 6.0845334538363}, {"id": 78, "src": 4, "dst": 7, "weight": 1.7402330786074258}, {"id": 79, "src": 10, "dst": 3, "weight": 1.0961784738940372}, {"id": 80, "src": 3, "dst": 5, "weight": 5.240926035069371}, {"id": 81, "src": 10, "dst": 1, "weight": 2.6429162308946097}, {"id": 82, "src": 8, "dst": 1, "weight": 6.42502540348407}, {"id": 83, "src": 3, "dst": 2, "weight": 4.5209819971341725}, {"id": 84, "src": 5, "dst": 7, "weight": 6.187348559314849}, {"id": 85, "src": 6, "dst": 10, "weight": 4.539043649973708}, {"id": 86, "src": 7, "dst": 6, "weight": 4.463487329207416}, {"id": 87, "src": 8, "dst": 2, "weight": 3.20060670303455}, {"id": 88, "src": 1, "dst": 7, "weight": 0.5070744102330551}, {"id": 89, "src": 7, "dst": 2, "weight": 0.6619663216215455}, {"id": 90, "src": 9, "dst": 7, "weight": 2.045503585528787}, {"id": 91, "src": 6, "dst": 7, "weight": 4.81595456876058}, {"id": 92, "src": 9, "dst": 2, "weight": 5.205729630468907}, {"id": 93, "src": 1, "dst": 9, "weight": 3.6711592943722167}, {"id": 94, "src": 7, "dst": 3, "weight": 3.880800714705231}, {"id": 95, "src": 6, "dst": 3, "weight": 0.5117528952938717}, {"id": 96, "src": 4, "dst": 9, "weight": 2.486310174290538}, {"id": 97, "src": 5, "dst": 6, "weight": 4.981529537633354}, {"id": 98, "src": 4, "dst": 9, "weight": 2.542229439376758}, {"id": 99, "src": 10, "dst": 3, "weight": 0.6281034837508404}, {"id": 100, "src": 8, "dst": 6, "weight": 2.506150338406953}]