[{"id": 1, "src": 19, "dst": 12, "weight": 4.5997918410708385}, {"id": 2, "src": 48, "dst": 46, "weight": 4.576568174843343}, {"id": 3, "src": 44, "dst": 49, "weight": 3.8172907021109532}, {"id": 4, "src": 17, "dst": 44, "weight": 3.1177406892354877}, {"id": 5, "src": 30, "dst": 27, "weight": 1.4651088451202579}, {"id": 6, "src": 26, "dst": 18, "weight": 6.336889009854271}, {"id": 7, "src": 27, "dst": 32, "weight": 5.226767286002181}, {"id": 8, "src": 16, "dst": 12, "weight": 1.2635832256878965}, {"id": 9, "src": 8, "dst": 26, "weight": 2.2664265349491353}, {"id": 10, "src": 33, "dst": 14, "weight": 5.1533292059110565}, {"id": 11, "src": 45, "dst": 37, "weight": 6.1964583565113305}, {"id": 12, "src": 14, "dst": 43, "weight": 2.401569896630485}, {"id": 13, "src": 27, "dst": 49, "weight": 2.2422035314482214}, {"id": 14, "src": 21, "dst": 14, "weight": 5.8017536116085004}, {"id": 15, "src": 3, "dst": 21, "weight": 5.899512547737996}, {"id": 16, "src": 44, "dst": 1, "weight": 2.5584459357403277}, {"id": 17, "src": 45, "dst": 30, "weight": 2.391401045664378}, {"id": 18, "src": 45, "dst": 28, "weight": 3.9443775789587967}, {"id": 19, "src": 27, "dst": 23, "weight": 3.2126908023666063}, {"id": 20, "src": 21, "dst": 34, "weight": 1.9259547005725557}, {"id": 21, "src": 19, "dst": 18, "weight": 1.2915358076832166}, {"id": 22, "src": 12, "dst": 17, "weight": 5.243772353677894}, {"id": 23, "src": 33, "dst": 10, "weight": 2.37148478359073}, {"id": 24, "src": 14, "dst": 6, "weight": 3.4680786310127116}, {"id": 25, "src": 32, "dst": 4, "weight": 4.702954316803268}, {"id": 26, "src": 7, "dst": 17, "weight": 3.103976650700916}, {"id": 27, "src": 29, "dst": 50, "weight": 4.512719344055764}, {"id": 28, "src": 13, "dst": 18, "weight": 4.1120732785141465}, {"id": 29, "src": 35, "dst": 36, "weight": 4.733145033424643}, {"id": 30, "src": 16, "dst": 35, "weight": 1.7061456101594237}, {"id": 31, "src": 20, "dst": 18, "weight": 4.677717567341485}, {"id": 32, "src": 10, "dst": 23, "weight": 6.4054509907992445}, {"id": 33, "src": 23, "dst": 2, "weight": 1.237610326775524}, {"id": 34, "src": 6, "dst": 23, "weight": 4.400241189700701}, {"id": 35, "src": 32, "dst": 48, "weight": 4.81452840909927}, {"id": 36, "src": 42, "dst": 18, "weight": 3.7190849509177957}, {"id": 37, "src": 24, "dst": 48, "weight": 5.53528820299412}, {"id": 38, "src": 45, "dst": 42, "weight": 2.3433812293439407}, {"id": 39, "src": 11, "dst": 24, "weight": 0.8142775744857025}, {"id": 40, "src": 45, "dst": 38, "weight": 1.6266642376309357}, {"id": 41, "src": 43, "dst": 21, "weight": 1.291851916456651}, {"id": 42, "src": 42, "dst": 37, "weight": 3.665210020796219}, {"id": 43, "src": 12, "dst": 22, "weight": 2.196553949704996}, {"id": 44, "src": 16, "dst": 8, "weight": 3.393660776926464}, {"id": 45, "src": 15, "dst": 38, "weight": 6.353041822133584}, {"id": 46, "src": 3, "dst": 36, "weight": 1.68353193165542}, {"id": 47, "src": 26, "dst": 4, "weight": 6.300128649172589}, {"id": 48, "src": 43, "dst": 22, "weight": 0.6665219569015179}, {"id": 49, "src": 29, "dst": 24, "weight": 5.540546912506783}, {"id": 50, "src": 30, "dst": 45, "weight": 5.201247480680365}, {"id": 51, "src": 9, "dst": 36, "weight": 2.9363961620428976}, {"id": 52, "src": 50, "dst": 18, "weight": 1.3185134921005999}, {"id": 53, "src": 29, "dst": 27, "weight": 0.5660535123393937}, {"id": 54, "src": 46, "dst": 47, "weight": 2.65957567850328}, {"id": 55, "src": 27, "dst": 22, "weight": 2.8857288535128487}, {"id": 56, "src": 42, "dst": 41, "weight": 3.1369313510563614}, {"id": 57, "src": 46, "dst": 26, "weight": 3.9059766098582718}, {"id": 58, "src": 50, "dst": 12, "weight": 1.3374775049318208}, {"id": 59, "src": 28, "dst": 2, "weight": 3.151565638292632}, {"id": 60, "src": 36, "dst": 12, "weight": 2.3568355241922436}, {"id": 61, "src": 32, "dst": 30, "weight": 3.687343185995813}, {"id": 62, "src": 35, "dst": 23, "weight": 1.4222866564373822}, {"id": 63, "src": 43, "dst": 37, "weight": 4.770233990648146}, {"id": 64, "src": 11, "dst": 38, "weight": 3.873662499738935}, {"id": 65, "src": 13, "dst": 34, "weight": 6.41700452858537}, {"id": 66, "src": 25, "dst": 20, "weight": 4.529387269991042}, {"id": 67, "src": 35, "dst": 10, "weight": 5.681421932858471}, {"id": 68, "src": 5, "dst": 21, "weight": 1.0405960863378967}, {"id": 69, "src": 3, "dst": 6, "weight": 3.002214601895565}, {"id": 70, "src": 39, "dst": 47, "weight": 6.069181896023512}, {"id": 71, "src": 8, "dst": 36, "weight": 5.69626005965287}, {"id": 72, "src": 21, "dst": 31, "weight": 0.568121691386718}, {"id": 73, "src": 43, "dst": 34, "weight": 2.0861062562753707}, {"id": 74, "src": 21, "dst": 18, "weight": 4.388029699276848}, {"id": 75, "src": 6, "dst": 37, "weight": 1.141802190240786}, {"id": 76, "src": 14, "dst": 2, "weight": 5.640686458532482}, {"id": 77, "src": 31, "dst": 11, "weight": 1.9855880432087991}, {"id": 78, "src": 12, "dst": 6, "weight": 5.52454732933904}, {"id": 79, "src": 23, "dst": 10, "weight": 2.126351401950778}, {"id": 80, "src": 50, "dst": 17, "weight": 1.5774555968527388}, {"id": 81, "src": 44, "dst": 43, "weight": 3.813620814076024}, {"id": 82, "src": 30, "dst": 37, "weight": 3.2736501724529345}, {"id": 83, "src": 37, "dst": 35, "weight": 4.340223225680282}, {"id": 84, "src": 41, "dst": 19, "weight": 1.2858538076876616}, {"id": 85, "src": 14, "dst": 6, "weight": 5.1895627194325415}, {"id": 86, "src": 50, "dst": 32, "weight": 5.727999553130225}, {"id": 87, "src": 39, "dst": 22, "weight": 5.4610147784371}, {"id": 88, "src": 30, "dst": 40, "weight": 5.2675175141284285}, {"id": 89, "src": 1, "dst": 24, "weight": 3.0429422110813142}, {"id": 90, "src": 10, "dst": 8, "weight": 2.3568424532643926}, {"id": 91, "src": 41, "dst": 38, "weight": 1.3659272699357088}, {"id": 92, "src": 24, "dst": 28, "weight": 5.115639334143013}, {"id": 93, "src": 50, "dst": 33, "weight": 5.985492561724146}, {"id": 94, "src": 48, "dst": 4, "weight": 5.636614267691183}, {"id": 95, "src": 18, "dst": 35, "weight": 3.971022890415492}, {"id": 96, "src": 30, "dst": 3, "weight": 1.8048080178343666}, {"id": 97, "src": 27, "dst": 9, "weight": 1.247265711335781}, {"id": 98, "src": 38, "dst": 10, "weight": 5.534574397661952}, {"id": 99, "src": 36, "dst": 10, "weight": 6.1274848247745295}, {"id": 100, "src": 17, "dst": 50, "weight": 3.632505646623039}, {"id": 101, "src": 21, "dst": 33, "weight": 2.155165709428516}, {"id": 102, "src": 14, "dst": 39, "weight": 4.878959277750733}, {"id": 103, "src": 18, "dst": 39, "weight": 6.003954447503917}, {"id": 104, "src": 29, "dst": 31, "weight": 4.83100538103059}, {"id": 105, "src": 16, "dst": 36, "weight": 3.0699689058663733}, {"id": 106, "src": 39, "dst": 14, "weight": 5.201247666476396}, {"id": 107, "src": 10, "dst": 2, "weight": 2.219325648595428}, {"id": 108, "src": 19, "dst": 34, "weight": 2.9495778825954533}, {"id": 109, "src": 14, "dst": 6, "weight": 1.425768687889307}, {"id": 110, "src": 2, "dst": 12, "weight": 1.3070031176072194}, {"id": 111, "src": 2, "dst": 42, "weight": 3.8142024122059617}, {"id": 112, "src": 37, "dst": 2, "weight": 5.3737720584248665}, {"id": 113, "src": 34, "dst": 47, "weight": 0.5081411343090461}, {"id": 114, "src": 32, "dst": 50, "weight": 2.7911924367442174}, {"id": 115, "src": 31, "dst": 32, "weight": 3.3276251269212365}, {"id": 116, "src": 1, "dst": 46, "weight": 4.486716627374486}, {"id": 117, "src": 28, "dst": 29, "weight": 1.1759646477820984}, {"id": 118, "src": 42, "dst": 20, "weight": 2.2898802445378834}, {"id": 119, "src": 13, "dst": 38, "weight": 5.849832465254117}, {"id": 120, "src": 33, "dst": 37, "weight": 6.43395076689579}, {"id": 121, "src": 6, "dst": 9, "weight": 5.664155587980252}, {"id": 122, "src": 11, "dst": 22, "weight": 1.9931246369544633}, {"id": 123, "src": 24, "dst": 28, "weight": 4.86757964585647}, {"id": 124, "src": 26, "dst": 40, "weight": 2.421523739795614}, {"id": 125, "src": 2, "dst": 13, "weight": 4.518046287960286}, {"id": 126, "src": 28, "dst": 17, "weight": 0.7641742878747306}, {"id": 127, "src": 5, "dst": 23, "weight": 3.988278498403229}, {"id": 128, "src": 8, "dst": 15, "weight": 2.2308479387313414}, {"id": 129, "src": 32, "dst": 45, "weight": 2.200181804358806}, {"id": 130, "src": 43, "dst": 18, "weight": 1.3484184441898992}, {"id": 131, "src": 14, "dst": 42, "weight": 2.6113502637257104}, {"id": 132, "src": 37, "dst": 11, "weight": 0.9236087771687504}, {"id": 133, "src": 19, "dst": 48, "weight": 4.113067334167719}, {"id": 134, "src": 18, "dst": 40, "weight": 1.8436573039102189}, {"id": 135, "src": 6, "dst": 2, "weight": 1.413169711045177}, {"id": 136, "src": 18, "dst": 27, "weight": 5.058379975287594}, {"id": 137, "src": 15, "dst": 36, "weight": 3.1140138778216024}, {"id": 138, "src": 22, "dst": 27, "weight": 0.904610042237501}, {"id": 139, "src": 15, "dst": 28, "weight": 4.896907507054086}, {"id": 140, "src": 7, "dst": 5, "weight": 3.56515896767325}, {"id": 141, "src": 18, "dst": 34, "weight": 5.940457232970929}, {"id": 142, "src": 9, "dst": 23, "weight": 6.355109108238302}, {"id": 143, "src": 22, "dst": 23, "weight": 2.3358542290555935}, {"id": 144, "src": 27, "dst": 4, "weight": 5.184904328538664}, {"id": 145, "src": 28, "dst": 1, "weight": 5.676507661478766}, {"id": 146, "src": 39, "dst": 2, "weight": 2.357140892810148}, {"id": 147, "src": 49, "dst": 50, "weight": 5.678489789268509}, {"id": 148, "src": 21, "dst": 18, "weight": 3.2892047885281777}, {"id": 149, "src": 41, "dst": 25, "weight": 2.1723058354061893}, {"id": 150, "src": 41, "dst": 36, "weight": 2.088694574093913}, {"id": 151, "src": 12, "dst": 31, "weight": 2.475360321184682}, {"id": 152, "src": 9, "dst": 10, "weight": 4.437422543268838}, {"id": 153, "src": 30, "dst": 1, "weight": 3.4510887581156053}, {"id": 154, "src": 18, "dst": 3, "weight": 4.409064425378646}, {"id": 155, "src": 11, "dst": 5, "weight": 2.9548716410964206}, {"id": 156, "src": 29, "dst": 21, "weight": 4.3278937472154}, {"id": 157, "src": 7, "dst": 14, "weight": 6.4881728928681355}, {"id": 158, "src": 13, "dst": 27, "weight": 2.609071462386211}, {"id": 159, "src": 6, "dst": 47, "weight": 5.261511290324947}, {"id": 160, "src": 18, "dst": 4, "weight": 4.8866474419195045}, {"id": 161, "src": 10, "dst": 39, "weight": 4.786334660238182}, {"id": 162, "src": 47, "dst": 32, "weight": 0.9150561402980266}, {"id": 163, "src": 50, "dst": 22, "weight": 6.395711358781179}, {"id": 164, "src": 25, "dst": 20, "weight": 1.757547442801103}, {"id": 165, "src": 35, "dst": 34, "weight": 1.4621726434974227}, {"id": 166, "src": 41, "dst": 6, "weight": 3.205576706518386}, {"id": 167, "src": 7, "dst": 35, "weight": 0.9711493497607973}, {"id": 168, "src": 39, "dst": 30, "weight": 5.733365675902609}, {"id": 169, "src": 30, "dst": 33, "weight": 4.33474840017257}, {"id": 170, "src": 42, "dst": 20, "weight": 3.2591311312814444}, {"id": 171, "src": 27, "dst": 24, "weight": 5.701027872294048}, {"id": 172, "src": 46, "dst": 33, "weight": 4.075645609527469}, {"id": 173, "src": 10, "dst": 46, "weight": 4.7885564461945656}, {"id": 174, "src": 41, "dst": 4, "weight": 3.960032968011618}, {"id": 175, "src": 26, "dst": 19, "weight": 5.1214328216223945}, {"id": 176, "src": 8, "dst": 31, "weight": 4.961337394478342}, {"id": 177, "src": 25, "dst": 2, "weight": 4.94190308503112}, {"id": 178, "src": 43, "dst": 34, "weight": 1.4642599940818688}, {"id": 179, "src": 43, "dst": 33, "weight": 3.599470322289715}, {"id": 180, "src": 43, "dst": 6, "weight": 2.3744388727782635}, {"id": 181, "src": 5, "dst": 18, "weight": 1.7408894168939717}, {"id": 182, "src": 26, "dst": 46, "weight": 5.234498700817827}, {"id": 183, "src": 37, "dst": 18, "weight": 4.300858876164098}, {"id": 184, "src": 23, "dst": 7, "weight": 4.664332800872601}, {"id": 185, "src": 41, "dst": 32, "weight": 0.9177031593788605}, {"id": 186, "src": 11, "dst": 2, "weight": 0.8623274146269306}, {"id": 187, "src": 19, "dst": 23, "weight": 4.7380856906762725}, {"id": 188, "src": 25, "dst": 44, "weight": 3.7375841592198302}, {"id": 189, "src": 50, "dst": 49, "weight": 3.0612763283681925}, {"id": 190, "src": 19, "dst": 24, "weight": 3.923231472377398}, {"id": 191, "src": 12, "dst": 24, "weight": 5.95217521083916}, {"id": 192, "src": 14, "dst": 23, "weight": 3.940617368009792}, {"id": 193, "src": 18, "dst": 45, "weight": 3.0995152031502116}, {"id": 194, "src": 29, "dst": 47, "weight": 2.43670727516567}, {"id": 195, "src": 15, "dst": 19, "weight": 3.763448375156261}, {"id": 196, "src": 35, "dst": 29, "weight": 6.44116173678292}, {"id": 197, "src": 9, "dst": 26, "weight": 5.014465898264192}, {"id": 198, "src": 13, "dst": 39, "weight": 4.343534885432662}, {"id": 199, "src": 5, "dst": 41, "weight": 4.754164482226114}, {"id": 200, "src": 19, "dst": 46, "weight": 4.840163740405191}, {"id": 201, "src": 15, "dst": 1, "weight": 4.358273732462081}, {"id": 202, "src": 14, "dst": 9, "weight": 0.7843002018462171}, {"id": 203, "src": 45, "dst": 15, "weight": 2.3147976353339597}, {"id": 204, "src": 19, "dst": 28, "weight": 2.5719957240102373}, {"id": 205, "src": 18, "dst": 6, "weight": 1.4117579450558837}, {"id": 206, "src": 46, "dst": 32, "weight": 1.5590748204625275}, {"id": 207, "src": 2, "dst": 8, "weight": 2.179843957510797}, {"id": 208, "src": 24, "dst": 28, "weight": 3.7932325305217525}, {"id": 209, "src": 1, "dst": 11, "weight": 5.066680697828768}, {"id": 210, "src": 24, "dst": 37, "weight": 6.182213508860686}, {"id": 211, "src": 30, "dst": 41, "weight": 0.6874408047155405}, {"id": 212, "src": 7, "dst": 12, "weight": 5.38745608057266}, {"id": 213, "src": 12, "dst": 3, "weight": 2.81560935055351}, {"id": 214, "src": 42, "dst": 4, "weight": 6.019398205619905}, {"id": 215, "src": 12, "dst": 46, "weight": 6.2090656500287755}, {"id": 216, "src": 37, "dst": 11, "weight": 5.208827232488889}, {"id": 217, "src": 38, "dst": 27, "weight": 1.353356331010209}, {"id": 218, "src": 16, "dst": 38, "weight": 0.6546847071061683}, {"id": 219, "src": 38, "dst": 17, "weight": 1.1505537576174858}, {"id": 220, "src": 44, "dst": 8, "weight": 4.495001289084305}, {"id": 221, "src": 30, "dst": 40, "weight": 2.5842314446920716}, {"id": 222, "src": 26, "dst": 17, "weight": 5.1360801767477575}, {"id": 223, "src": 17, "dst": 49, "weight": 3.944671873736187}, {"id": 224, "src": 40, "dst": 50, "weight": 6.229527921517751}, {"id": 225, "src": 49, "dst": 15, "weight": 4.364993401515937}, {"id": 226, "src": 35, "dst": 24, "weight": 5.288298509811904}, {"id": 227, "src": 35, "dst": 6, "weight": 3.10038310871787}, {"id": 228, "src": 20, "dst": 7, "weight": 4.53044293387069}, {"id": 229, "src": 16, "dst": 1, "weight": 5.510179670049368}, {"id": 230, "src": 23, "dst": 10, "weight": 3.506972559050606}, {"id": 231, "src": 5, "dst": 27, "weight": 4.948239768852268}, {"id": 232, "src": 34, "dst": 24, "weight": 3.0254186842676307}, {"id": 233, "src": 43, "dst": 36, "weight": 1.2151389626927667}, {"id": 234, "src": 15, "dst": 48, "weight": 0.7817913000621968}, {"id": 235, "src": 21, "dst": 4, "weight": 1.040547270897951}, {"id": 236, "src": 40, "dst": 41, "weight": 5.5215433784447825}, {"id": 237, "src": 37, "dst": 43, "weight": 1.6122463495646264}, {"id": 238, "src": 3, "dst": 32, "weight": 5.45910593374552}, {"id": 239, "src": 50, "dst": 45, "weight": 4.759177319778436}, {"id": 240, "src": 1, "dst": 9, "weight": 2.6507669081156555}, {"id": 241, "src": 5, "dst": 26, "weight": 2.7660293134271994}, {"id": 242, "src": 29, "dst": 18, "weight": 5.920659097904984}, {"id": 243, "src": 11, "dst": 43, "weight": 2.7325624265801602}, {"id": 244, "src": 37, "dst": 22, "weight": 2.5357433448979365}, {"id": 245, "src": 10, "dst": 44, "weight": 0.9565254208350387}, {"id": 246, "src": 16, "dst": 28, "weight": 4.307941098614854}, {"id": 247, "src": 24, "dst": 25, "weight": 2.918934343423616}, {"id": 248, "src": 15, "dst": 46, "weight": 2.8457218432921456}, {"id": 249, "src": 12, "dst": 7, "weight": 3.662696841214623}, {"id": 250, "src": 5, "dst": 48, "weight": 4.038424948282934}, {"id": 251, "src": 39, "dst": 36, "weight": 6.175152114338356}, {"id": 252, "src": 22, "dst": 48, "weight": 2.570923380217394}, {"id": 253, "src": 13, "dst": 5, "weight": 4.492205308643063}, {"id": 254, "src": 22, "dst": 17, "weight": 5.697923469045011}, {"id": 255, "src": 27, "dst": 33, "weight": 4.588547343074124}, {"id": 256, "src": 12, "dst": 38, "weight": 2.587825767731868}, {"id": 257, "src": 42, "dst": 39, "weight": 1.5701897768332975}, {"id": 258, "src": 6, "dst": 50, "weight": 4.479739520874882}, {"id": 259, "src": 19, "dst": 26, "weight": 5.233124719300857}, {"id": 260, "src": 30, "dst": 34, "weight": 5.427153118348007}, {"id": 261, "src": 27, "dst": 47, "weight": 3.5801601867452773}, {"id": 262, "src": 30, "dst": 27, "weight": 3.2811598706993035}, {"id": 263, "src": 6, "dst": 10, "weight": 2.8870515736388658}, {"id": 264, "src": 19, "dst": 7, "weight": 4.262547612247552}, {"id": 265, "src": 20, "dst": 11, "weight": 0.6412084442249337}, {"id": 266, "src": 13, "dst": 16, "weight": 1.3814205965685002}, {"id": 267, "src": 8, "dst": 18, "weight": 3.7220175586210296}, {"id": 268, "src": 25, "dst": 26, "weight": 2.8272445539169997}, {"id": 269, "src": 4, "dst": 14, "weight": 5.018405585669327}, {"id": 270, "src": 43, "dst": 10, "weight": 3.1874815007266393}, {"id": 271, "src": 48, "dst": 41, "weight": 3.800550798108472}, {"id": 272, "src": 7, "dst": 12, "weight": 5.350737354343941}, {"id": 273, "src": 41, "dst": 25, "weight": 6.360552613214412}, {"id": 274, "src": 29, "dst": 4, "weight": 3.377189264911314}, {"id": 275, "src": 36, "dst": 28, "weight": 2.842465096886877}, {"id": 276, "src": 44, "dst": 6, "weight": 1.4879362023065963}, {"id": 277, "src": 27, "dst": 50, "weight": 5.1648364253930215}, {"id": 278, "src": 10, "dst": 43, "weight": 3.4483198540129116}, {"id": 279, "src": 50, "dst": 16, "weight": 2.5554946682360877}, {"id": 280, "src": 50, "dst": 32, "weight": 1.5675064014550477}, {"id": 281, "src": 36, "dst": 33, "weight": 4.132987107990143}, {"id": 282, "src": 35, "dst": 9, "weight": 6.3658861514408684}, {"id": 283, "src": 1, "dst": 9, "weight": 5.4891609112267385}, {"id": 284, "src": 41, "dst": 8, "weight": 4.607299988789885}, {"id": 285, "src": 2, "dst": 39, "weight": 4.718276742056855}, {"id": 286, "src": 39, "dst": 31, "weight": 1.872369062488089}, {"id": 287, "src": 12, "dst": 3, "weight": 2.262425851817486}, {"id": 288, "src": 8, "dst": 24, "weight": 4.930992768130929}, {"id": 289, "src": 50, "dst": 22, "weight": 5.646635244961065}, {"id": 290, "src": 25, "dst": 2, "weight": 0.9061420906119784}, {"id": 291, "src": 38, "dst": 4, "weight": 6.185451933531813}, {"id": 292, "src": 40, "dst": 7, "weight": 2.8779825860468593}, {"id": 293, "src": 28, "dst": 38, "weight": 3.3048472695759674}, {"id": 294, "src": 20, "dst": 35, "weight": 2.9853019716783056}, {"id": 295, "src": 46, "dst": 43, "weight": 3.6076791636569867}, {"id": 296, "src": 19, "dst": 5, "weight": 1.5550938796925122}, {"id": 297, "src": 6, "dst": 3, "weight": 2.037745186192522}, {"id": 298, "src": 42, "dst": 32, "weight": 3.9095507572857082}, {"id": 299, "src": 42, "dst": 6, "weight": 0.9716617471702562}, {"id": 300, "src": 42, "dst": 25, "weight": 2.661275819470702}, {"id": 301, "src": 49, "dst": 43, "weight": 3.7322547709571348}, {"id": 302, "src": 21, "dst": 2, "weight": 0.5919493010848438}, {"id": 303, "src": 37, "dst": 9, "weight": 3.5418790215639753}, {"id": 304, "src": 7, "dst": 9, "weight": 3.918437441627087}, {"id": 305, "src": 36, "dst": 5, "weight": 4.352297487920819}, {"id": 306, "src": 6, "dst": 30, "weight": 2.2501143125071006}, {"id": 307, "src": 15, "dst": 37, "weight": 2.435518292025254}, {"id": 308, "src": 4, "dst": 26, "weight": 4.574215888564788}, {"id": 309, "src": 27, "dst": 33, "weight": 2.5522675230361864}, {"id": 310, "src": 44, "dst": 39, "weight": 3.2743057052161575}, {"id": 311, "src": 38, "dst": 1, "weight": 5.316988804008501}, {"id": 312, "src": 16, "dst": 41, "weight": 2.0514275142321936}, {"id": 313, "src": 22, "dst": 40, "weight": 4.1337372290728815}, {"id": 314, "src": 10, "dst": 6, "weight": 4.735862475314818}, {"id": 315, "src": 39, "dst": 3, "weight": 4.976849667368971}, {"id": 316, "src": 30, "dst": 15, "weight": 2.539020163301969}, {"id": 317, "src": 48, "dst": 47, "weight": 3.7583892479891046}, {"id": 318, "src": 17, "dst": 26, "weight": 2.5591502024546697}, {"id": 319, "src": 14, "dst": 25, "weight": 3.068150074434515}, {"id": 320, "src": 3, "dst": 41, "weight": 5.7460871702311795}, {"id": 321, "src": 23, "dst": 28, "weight": 2.016007166443572}, {"id": 322, "src": 3, "dst": 15, "weight": 4.350043436663811}, {"id": 323, "src": 39, "dst": 22, "weight": 4.858588991164671}, {"id": 324, "src": 10, "dst": 6, "weight": 3.0510833064592706}, {"id": 325, "src": 14, "dst": 44, "weight": 5.482193775719807}, {"id": 326, "src": 37, "dst": 19, "weight": 3.5189848099792522}, {"id": 327, "src": 43, "dst": 26, "weight": 1.7717950001048506}, {"id": 328, "src": 38, "dst": 47, "weight": 3.961867939706715}, {"id": 329, "src": 25, "dst": 38, "weight": 1.8377367993468823}, {"id": 330, "src": 42, "dst": 22, "weight": 3.405205400834392}, {"id": 331, "src": 11, "dst": 5, "weight": 6.197401793268408}, {"id": 332, "src": 32, "dst": 5, "weight": 3.0759098293647646}, {"id": 333, "src": 42, "dst": 19, "weight": 3.969056896764732}, {"id": 334, "src": 19, "dst": 12, "weight": 1.737421267984611}, {"id": 335, "src": 32, "dst": 43, "weight": 6.17904241155167}, {"id": 336, "src": 26, "dst": 35, "weight": 3.3945297118427753}, {"id": 337, "src": 5, "dst": 23, "weight": 6.4995826669855274}, {"id": 338, "src": 42, "dst": 28, "weight": 5.669929659098781}, {"id": 339, "src": 10, "dst": 1, "weight": 2.4490149828490133}, {"id": 340, "src": 5, "dst": 19, "weight": 5.827045143169784}, {"id": 341, "src": 2, "dst": 22, "weight": 2.6769102969963643}, {"id": 342, "src": 23, "dst": 41, "weight": 0.6873841140289367}, {"id": 343, "src": 5, "dst": 50, "weight": 4.58121830831185}, {"id": 344, "src": 27, "dst": 45, "weight": 4.294680945675832}, {"id": 345, "src": 49, "dst": 40, "weight": 4.896844733167786}, {"id": 346, "src": 17, "dst": 3, "weight": 4.849661523978828}, {"id": 347, "src": 17, "dst": 5, "weight": 5.513727035623837}, {"id": 348, "src": 23, "dst": 32, "weight": 2.2989235540266026}, {"id": 349, "src": 1, "dst": 23, "weight": 4.606905223304565}, {"id": 350, "src": 30, "dst": 35, "weight": 3.345179364301594}, {"id": 351, "src": 26, "dst": 19, "weight": 4.1665264349100335}, {"id": 352, "src": 15, "dst": 27, "weight": 2.542770234193779}, {"id": 353, "src": 48, "dst": 20, "weight": 0.5995796881277182}, {"id": 354, "src": 6, "dst": 29, "weight": 1.1571555304091565}, {"id": 355, "src": 6, "dst": 27, "weight": 4.1860763145038415}, {"id": 356, "src": 13, "dst": 33, "weight": 1.825987224877598}, {"id": 357, "src": 47, "dst": 35, "weight": 5.005640655420743}, {"id": 358, "src": 47, "dst": 39, "weight": 6.291000891767403}, {"id": 359, "src": 7, "dst": 4, "weight": 5.391723642445377}, {"id": 360, "src": 49, "dst": 24, "weight": 4.543708485300615}, {"id": 361, "src": 19, "dst": 50, "weight": 5.90196502811892}, {"id": 362, "src": 40, "dst": 4, "weight": 5.009474736518522}, {"id": 363, "src": 9, "dst": 34, "weight": 1.5317927714291704}, {"id": 364, "src": 1, "dst": 9, "weight": 6.393279579410227}, {"id": 365, "src": 26, "dst": 29, "weight": 0.6149476186282725}, {"id": 366, "src": 30, "dst": 38, "weight": 0.6132406367223473}, {"id": 367, "src": 18, "dst": 21, "weight": 1.604129987549885}, {"id": 368, "src": 18, "dst": 8, "weight": 0.5226790503608933}, {"id": 369, "src": 28, "dst": 29, "weight": 1.6512672670815107}, {"id": 370, "src": 41, "dst": 50, "weight": 2.5571414403304686}, {"id": 371, "src": 5, "dst": 26, "weight": 0.6276495719476667}, {"id": 372, "src": 8, "dst": 43, "weight": 1.971246764398728}, {"id": 373, "src": 4, "dst": 37, "weight": 4.31475721341814}, {"id": 374, "src": 8, "dst": 28, "weight": 6.4055047930703495}, {"id": 375, "src": 1, "dst": 33, "weight": 3.8213754001304387}, {"id": 376, "src": 43, "dst": 31, "weight": 3.4664985663998467}, {"id": 377, "src": 45, "dst": 25, "weight": 1.4624307665851055}, {"id": 378, "src": 10, "dst": 29, "weight": 4.733565478678214}, {"id": 379, "src": 46, "dst": 16, "weight": 3.4116031586820683}, {"id": 380, "src": 43, "dst": 2, "weight": 5.6147407881913765}, {"id": 381, "src": 12, "dst": 11, "weight": 6.299452456163386}, {"id": 382, "src": 9, "dst": 6, "weight": 3.2010908379904426}, {"id": 383, "src": 22, "dst": 40, "weight": 3.966366188362067}, {"id": 384, "src": 3, "dst": 10, "weight": 1.6915014944548865}, {"id": 385, "src": 47, "dst": 36, "weight": 2.114809382381158}, {"id": 386, "src": 49, "dst": 5, "weight": 6.076700108765599}, {"id": 387, "src": 14, "dst": 39, "weight": 2.8470516736592875}, {"id": 388, "src": 23, "dst": 13, "weight": 5.266481263425619}, {"id": 389, "src": 8, "dst": 29, "weight": 5.576498888823819}, {"id": 390, "src": 20, "dst": 33, "weight": 5.938873926266117}, {"id": 391, "src": 44, "dst": 25, "weight": 2.4818496528082052}, {"id": 392, "src": 38, "dst": 28, "weight": 5.930454857536372}, {"id": 393, "src": 35, "dst": 20, "weight": 1.133893794148664}, {"id": 394, "src": 45, "dst": 47, "weight": 2.887429985575836}, {"id": 395, "src": 4, "dst": 38, "weight": 0.877590641828105}, {"id": 396, "src": 24, "dst": 44, "weight": 2.1518431069068376}, {"id": 397, "src": 15, "dst": 27, "weight": 5.383677063771083}, {"id": 398, "src": 38, "dst": 49, "weight": 2.1804885491851147}, {"id": 399, "src": 32, "dst": 9, "weight": 3.902779136550871}, {"id": 400, "src": 9, "dst": 45, "weight": 1.9505578190127757}, {"id": 401, "src": 18, "dst": 36, "weight": 4.539838812122466}, {"id": 402, "src": 2, "dst": 21, "weight": 1.9972101413791314}, {"id": 403, "src": 13, "dst": 25, "weight": 2.4224365544543836}, {"id": 404, "src": 20, "dst": 32, "weight": 4.000572482023131}, {"id": 405, "src": 30, "dst": 39, "weight": 5.952630186884472}, {"id": 406, "src": 34, "dst": 23, "weight": 1.861925713133792}, {"id": 407, "src": 32, "dst": 38, "weight": 3.522417185897984}, {"id": 408, "src": 17, "dst": 44, "weight": 2.729498096999942}, {"id": 409, "src": 9, "dst": 6, "weight": 1.2682308746487663}, {"id": 410, "src": 12, "dst": 16, "weight": 3.802855340779711}, {"id": 411, "src": 39, "dst": 8, "weight": 6.4829664499608555}, {"id": 412, "src": 16, "dst": 40, "weight": 6.381702084761686}, {"id": 413, "src": 27, "dst": 33, "weight": 2.6613481633474407}, {"id": 414, "src": 49, "dst": 28, "weight": 4.449049994428592}, {"id": 415, "src": 42, "dst": 32, "weight": 4.829637447945277}, {"id": 416, "src": 27, "dst": 38, "weight": 0.8662961514746446}, {"id": 417, "src": 48, "dst": 3, "weight": 1.3702956952839844}, {"id": 418, "src": 16, "dst": 22, "weight": 2.34978116111541}, {"id": 419, "src": 34, "dst": 27, "weight": 1.1967728266626596}, {"id": 420, "src": 50, "dst": 6, "weight": 6.189725377136007}, {"id": 421, "src": 12, "dst": 30, "weight": 6.397456179567945}, {"id": 422, "src": 3, "dst": 14, "weight": 5.308335003220066}, {"id": 423, "src": 4, "dst": 20, "weight": 6.4448597233469265}, {"id": 424, "src": 40, "dst": 2, "weight": 6.455770708571014}, {"id": 425, "src": 45, "dst": 28, "weight": 2.807704781298792}, {"id": 426, "src": 8, "dst": 3, "weight": 6.2304392241803255}, {"id": 427, "src": 18, "dst": 50, "weight": 0.8760000018910346}, {"id": 428, "src": 40, "dst": 18, "weight": 1.4877102776590003}, {"id": 429, "src": 23, "dst": 34, "weight": 1.4045899534588413}, {"id": 430, "src": 32, "dst": 37, "weight": 5.2365881872429325}, {"id": 431, "src": 4, "dst": 42, "weight": 4.423964946203206}, {"id": 432, "src": 27, "dst": 20, "weight": 0.7858272565778499}, {"id": 433, "src": 8, "dst": 25, "weight": 2.459730436447439}, {"id": 434, "src": 25, "dst": 33, "weight": 4.772505152721288}, {"id": 435, "src": 39, "dst": 8, "weight": 2.8354778700064043}, {"id": 436, "src": 11, "dst": 23, "weight": 1.3210842258551092}, {"id": 437, "src": 49, "dst": 44, "weight": 2.6869769717286838}, {"id": 438, "src": 13, "dst": 18, "weight": 5.3885367276175415}, {"id": 439, "src": 28, "dst": 39, "weight": 1.1718628496243502}, {"id": 440, "src": 41, "dst": 44, "weight": 4.216473736940361}, {"id": 441, "src": 4, "dst": 37, "weight": 6.339582450059771}, {"id": 442, "src": 4, "dst": 19, "weight": 5.381075340519905}, {"id": 443, "src": 22, "dst": 39, "weight": 2.7636423144342577}, {"id": 444, "src": 21, "dst": 45, "weight": 3.666858313784275}, {"id": 445, "src": 13, "dst": 6, "weight": 5.794296064659213}, {"id": 446, "src": 31, "dst": 1, "weight": 6.184390845238993}, {"id": 447, "src": 8, "dst": 39, "weight": 5.790803993284043}, {"id": 448, "src": 21, "dst": 22, "weight": 1.0122537908511209}, {"id": 449, "src": 46, "dst": 13, "weight": 0.5738349617359901}, {"id": 450, "src": 27, "dst": 37, "weight": 4.920632230492548}, {"id": 451, "src": 28, "dst": 21, "weight": 1.002671688829037}, {"id": 452, "src": 42, "dst": 26, "weight": 3.2576925939557615}, {"id": 453, "src": 45, "dst": 20, "weight": 5.7455589537524805}, {"id": 454, "src": 18, "dst": 29, "weight": 3.2010928948206363}, {"id": 455, "src": 7, "dst": 38, "weight": 0.8345269331908107}, {"id": 456, "src": 12, "dst": 25, "weight": 1.628520936042097}, {"id": 457, "src": 9, "dst": 34, "weight": 4.151596271273075}, {"id": 458, "src": 8, "dst": 40, "weight": 5.189532536433622}, {"id": 459, "src": 50, "dst": 20, "weight": 3.748756980638512}, {"id": 460, "src": 14, "dst": 43, "weight": 1.3495148575034113}, {"id": 461, "src": 21, "dst": 47, "weight": 2.7931045798579155}, {"id": 462, "src": 36, "dst": 37, "weight": 6.4690976164578515}, {"id": 463, "src": 43, "dst": 16, "weight": 3.483775379267506}, {"id": 464, "src": 47, "dst": 11, "weight": 1.029497592881551}, {"id": 465, "src": 38, "dst": 1, "weight": 5.054083192227193}, {"id": 466, "src": 15, "dst": 12, "weight": 5.727753391004091}, {"id": 467, "src": 11, "dst": 50, "weight": 5.994735294457882}, {"id": 468, "src": 33, "dst": 13, "weight": 4.341654688768486}, {"id": 469, "src": 30, "dst": 12, "weight": 6.1564341583979365}, {"id": 470, "src": 45, "dst": 15, "weight": 1.2817912234314106}, {"id": 471, "src": 48, "dst": 40, "weight": 2.4418930848860194}, {"id": 472, "src": 45, "dst": 16, "weight": 1.499887137192007}, {"id": 473, "src": 9, "dst": 23, "weight": 4.913044153196358}, {"id": 474, "src": 4, "dst": 47, "weight": 1.336361844145422}, {"id": 475, "src": 28, "dst": 44, "weight": 1.0549952032822112}, {"id": 476, "src": 5, "dst": 3, "weight": 1.64489882642155}, {"id": 477, "src": 25, "dst": 12, "weight": 1.0633829652445057}, {"id": 478, "src": 50, "dst": 27, "weight": 5.808370513408384}, {"id": 479, "src": 28, "dst": 14, "weight": 6.143905226483547}, {"id": 480, "src": 10, "dst": 24, "weight": 4.718892850870369}, {"id": 481, "src": 44, "dst": 20, "weight": 2.21183237095733}, {"id": 482, "src": 30, "dst": 29, "weight": 1.4622989136899767}, {"id": 483, "src": 48, "dst": 34, "weight": 1.147040970983843}, {"id": 484, "src": 9, "dst": 45, "weight": 4.746748555717557}, {"id": 485, "src": 43, "dst": 32, "weight": 5.6649581282767105}, {"id": 486, "src": 36, "dst": 22, "weight": 2.965570307191976}, {"id": 487, "src": 44, "dst": 23, "weight": 3.2177833684664296}, {"id": 488, "src": 4, "dst": 1, "weight": 2.2161056232766905}, {"id": 489, "src": 40, "dst": 19, "weight": 5.562982722517841}, {"id": 490, "src": 49, "dst": 26, "weight": 2.049437775564739}, {"id": 491, "src": 41, "dst": 50, "weight": 5.832529642605803}, {"id": 492, "src": 46, "dst": 6, "weight": 1.3230003993552781}, {"id": 493, "src": 42, "dst": 45, "weight": 2.8607504620260062}, {"id": 494, "src": 41, "dst": 8, "weight": 1.0914583485366844}, {"id": 495, "src": 45, "dst": 36, "weight": 2.613730047677419}, {"id": 496, "src": 44, "dst": 37, "weight": 3.27125365727274}, {"id": 497, "src": 46, "dst": 41, "weight": 6.0901454325540065}, {"id": 498, "src": 29, "dst": 19, "weight": 5.041761066409708}, {"id": 499, "src": 25, "dst": 28, "weight": 6.283709337377385}, {"id": 500, "src": 48, "dst": 44, "weight": 0.7843931918732536}]